wiring/__init__.py
wiring/_to_multi_platform_converter.py
wiring/_utils/find.py
wiring/bot_base.py
wiring/errors/action_not_supported_error.py
wiring/errors/bot_api_error.py
wiring/errors/not_found_error.py
wiring/errors/not_messageable_chat_error.py
wiring/multi_platform_bot.py
wiring/multi_platform_resources.py
wiring/platforms/discord/__init__.py
wiring/platforms/discord/_entities_converter.py
wiring/platforms/discord/channels.py
wiring/platforms/telegram/__init__.py
wiring/platforms/telegram/_entities_converter.py
wiring/platforms/twitch/__init__.py
wiring/platforms/twitch/_entities_converter.py
wiring-0.1.2.dist-info/LICENSE
wiring-0.1.2.dist-info/METADATA
wiring-0.1.2.dist-info/WHEEL
wiring-0.1.2.dist-info/RECORD
