Metadata-Version: 2.1
Name: wiring
Version: 0.1.2
Summary: package for building bots that run on multiple platforms, like discord and telegram
Home-page: https://github.com/crucials/wiring
License: MIT
Keywords: wiring,discord.py,bot,python-telegram-bot,twitchio
Requires-Python: >=3.8
Classifier: Development Status :: 4 - Beta
Classifier: Intended Audience :: Developers
Classifier: License :: OSI Approved :: MIT License
Classifier: Natural Language :: English
Classifier: Operating System :: OS Independent
Classifier: Programming Language :: Python :: 3
Classifier: Programming Language :: Python :: 3.8
Classifier: Programming Language :: Python :: 3.9
Classifier: Programming Language :: Python :: 3.10
Classifier: Programming Language :: Python :: 3.11
Classifier: Programming Language :: Python :: 3.12
Classifier: Topic :: Internet
Classifier: Topic :: Software Development :: Libraries
Classifier: Topic :: Software Development :: Libraries :: Python Modules
Classifier: Topic :: Utilities
Classifier: Typing :: Typed
Provides-Extra: discord
Provides-Extra: telegram
Provides-Extra: twitch
Requires-Dist: discord-py (>=2.4.0,<3.0.0) ; extra == "discord"
Requires-Dist: python-telegram-bot (>=21.4,<22.0) ; extra == "telegram"
Requires-Dist: twitchio (>=2.10.0,<3.0.0) ; extra == "twitch"
Project-URL: Documentation, https://github.com/crucials/wiring/wiki
Project-URL: Repository, https://github.com/crucials/wiring
Project-URL: report an issues, https://github.com/crucials/wiring/issues
